wslwinreg/__init__.py
wslwinreg/common.py
wslwinreg/cygwinapi.py
wslwinreg/nullapi.py
wslwinreg/wslapi.py
wslwinreg/bin/backend-arm.exe
wslwinreg/bin/backend-arm64.exe
wslwinreg/bin/backend-x64.exe
wslwinreg/bin/backend-x86.exe
wslwinreg-1.1.2.dist-info/licenses/LICENSE.txt
wslwinreg-1.1.2.dist-info/METADATA
wslwinreg-1.1.2.dist-info/WHEEL
wslwinreg-1.1.2.dist-info/top_level.txt
wslwinreg-1.1.2.dist-info/RECORD
